{
  "bbox": {
    "south": 46.372652,
    "west": 13.345766,
    "north": 47.033758500000005,
    "east": 15.253173
  },
  "poiCount": 146,
  "leafCount": 0,
  "averagePosition": [
    14.543498402054796,
    46.58872317602741
  ],
  "data": [],
  "children": [
    {
      "bbox": {
        "south": 46.372652,
        "west": 13.345766,
        "north": 46.70320525,
        "east": 14.2994695
      },
      "poiCount": 36,
      "leafCount": 36,
      "averagePosition": [
        13.978491344444445,
        46.526834055555554
      ],
      "data": [
        {
          "type": "Feature",
          "properties": {
            "id": "1033077678",
            "osm_type": "node",
            "lat": 46.6024334,
            "lon": 13.441449,
            "natural": "scrub"
          },
          "geometry": {
            "type": "Point",
            "coordinates": [
              13.441449,
              46.6024334
            ]
          }
        },
        {
          "type": "Feature",
          "properties": {
            "id": "2495287030",
            "osm_type": "node",
            "lat": 46.6344408,
            "lon": 13.3577495,
            "name": "Gösseringgraben",
            "natural": "yes"
          },
          "geometry": {
            "type": "Point",
            "coordinates": [
              13.3577495,
              46.6344408
            ]
          }
        },
        {
          "type": "Feature",
          "properties": {
            "id": "334877586",
            "osm_type": "node",
            "lat": 46.5844,
            "lon": 13.7318665,
            "natural": "cliff"
          },
          "geometry": {
            "type": "Point",
            "coordinates": [
              13.7318665,
              46.5844
            ]
          }
        },
        {
          "type": "Feature",
          "properties": {
            "id": "1847410577",
            "osm_type": "node",
            "lat": 46.6635823,
            "lon": 13.9704841,
            "natural": "beach",
            "sport": "swimming"
          },
          "geometry": {
            "type": "Point",
            "coordinates": [
              13.9704841,
              46.6635823
            ]
          }
        },
        {
          "type": "Feature",
          "properties": {
            "id": "1847410596",
            "osm_type": "node",
            "lat": 46.6641465,
            "lon": 13.9713277,
            "natural": "beach",
            "sport": "swimming"
          },
          "geometry": {
            "type": "Point",
            "coordinates": [
              13.9713277,
              46.6641465
            ]
          }
        },
        {
          "type": "Feature",
          "properties": {
            "id": "2914618328",
            "osm_type": "node",
            "lat": 46.4218672,
            "lon": 13.7802599,
            "name": "Zadnje okno",
            "natural": "cliff"
          },
          "geometry": {
            "type": "Point",
            "coordinates": [
              13.7802599,
              46.4218672
            ]
          }
        },
        {
          "type": "Feature",
          "properties": {
            "id": "4789975896",
            "osm_type": "node",
            "lat": 46.6751571,
            "lon": 13.9573045,
            "climbing:quality": "mixed",
            "climbing:rock": "slate",
            "climbing:sport": "26",
            "fee": "no",
            "highway": "via_ferrata",
            "name": "Peterlewand",
            "natural": "cliff",
            "note": "The cliff has 6 short via ferrata.",
            "sport": "climbing",
            "via_ferrata_scale": "1",
            "website": "https://climbing.plus/klettern/66-peterlewand-st-urban-ossiacher-see",
            "wheelchair": "no"
          },
          "geometry": {
            "type": "Point",
            "coordinates": [
              13.9573045,
              46.6751571
            ]
          }
        },
        {
          "type": "Feature",
          "properties": {
            "id": "5843906341",
            "osm_type": "node",
            "lat": 46.5843408,
            "lon": 13.7318173,
            "natural": "cliff"
          },
          "geometry": {
            "type": "Point",
            "coordinates": [
              13.7318173,
              46.5843408
            ]
          }
        },
        {
          "type": "Feature",
          "properties": {
            "id": "12012462833",
            "osm_type": "node",
            "lat": 46.5736951,
            "lon": 13.6070828,
            "natural": "shrub"
          },
          "geometry": {
            "type": "Point",
            "coordinates": [
              13.6070828,
              46.5736951
            ]
          }
        },
        {
          "type": "Feature",
          "properties": {
            "id": "12060012217",
            "osm_type": "node",
            "lat": 46.5402703,
            "lon": 13.6476815,
            "natural": "shrub"
          },
          "geometry": {
            "type": "Point",
            "coordinates": [
              13.6476815,
              46.5402703
            ]
          }
        },
        {
          "type": "Feature",
          "properties": {
            "id": "12066216353",
            "osm_type": "node",
            "lat": 46.5434706,
            "lon": 13.6524844,
            "natural": "tree_stump"
          },
          "geometry": {
            "type": "Point",
            "coordinates": [
              13.6524844,
              46.5434706
            ]
          }
        },
        {
          "type": "Feature",
          "properties": {
            "id": "12125411797",
            "osm_type": "node",
            "lat": 46.4162964,
            "lon": 13.6095185,
            "natural": "shrub"
          },
          "geometry": {
            "type": "Point",
            "coordinates": [
              13.6095185,
              46.4162964
            ]
          }
        },
        {
          "type": "Feature",
          "properties": {
            "id": "12125411798",
            "osm_type": "node",
            "lat": 46.416383,
            "lon": 13.6095967,
            "natural": "shrub"
          },
          "geometry": {
            "type": "Point",
            "coordinates": [
              13.6095967,
              46.416383
            ]
          }
        },
        {
          "type": "Feature",
          "properties": {
            "id": "12125411799",
            "osm_type": "node",
            "lat": 46.4163202,
            "lon": 13.6096692,
            "natural": "shrub"
          },
          "geometry": {
            "type": "Point",
            "coordinates": [
              13.6096692,
              46.4163202
            ]
          }
        },
        {
          "type": "Feature",
          "properties": {
            "id": "12125411800",
            "osm_type": "node",
            "lat": 46.4162597,
            "lon": 13.6096811,
            "natural": "shrub"
          },
          "geometry": {
            "type": "Point",
            "coordinates": [
              13.6096811,
              46.4162597
            ]
          }
        },
        {
          "type": "Feature",
          "properties": {
            "id": "12350589630",
            "osm_type": "node",
            "lat": 46.58293,
            "lon": 13.7329026,
            "natural": "cliff"
          },
          "geometry": {
            "type": "Point",
            "coordinates": [
              13.7329026,
              46.58293
            ]
          }
        },
        {
          "type": "Feature",
          "properties": {
            "id": "3564256731",
            "osm_type": "node",
            "lat": 46.6234036,
            "lon": 14.1920034,
            "height": "2",
            "name": "Weiberzahn",
            "natural": "stone",
            "width": "2"
          },
          "geometry": {
            "type": "Point",
            "coordinates": [
              14.1920034,
              46.6234036
            ]
          }
        },
        {
          "type": "Feature",
          "properties": {
            "id": "6143690587",
            "osm_type": "node",
            "lat": 46.3958321,
            "lon": 14.2705197,
            "height": "18 m",
            "name": "Tominčev slap",
            "natural": "yes",
            "waterway": "waterfall",
            "wikidata": "Q12804276",
            "wikimedia_commons": "File:Tominčev slap.jpg",
            "wikipedia": "sl:Tominčev slap"
          },
          "geometry": {
            "type": "Point",
            "coordinates": [
              14.2705197,
              46.3958321
            ]
          }
        },
        {
          "type": "Feature",
          "properties": {
            "id": "6195854963",
            "osm_type": "node",
            "lat": 46.5435478,
            "lon": 14.2550129,
            "name": "Köttmannsdorfer Hafen",
            "natural": "bay"
          },
          "geometry": {
            "type": "Point",
            "coordinates": [
              14.2550129,
              46.5435478
            ]
          }
        },
        {
          "type": "Feature",
          "properties": {
            "id": "6684072341",
            "osm_type": "node",
            "lat": 46.6191948,
            "lon": 14.1481258,
            "name": "Teixlbucht",
            "natural": "bay"
          },
          "geometry": {
            "type": "Point",
            "coordinates": [
              14.1481258,
              46.6191948
            ]
          }
        },
        {
          "type": "Feature",
          "properties": {
            "id": "7397983576",
            "osm_type": "node",
            "lat": 46.4422787,
            "lon": 14.1862942,
            "natural": "stone"
          },
          "geometry": {
            "type": "Point",
            "coordinates": [
              14.1862942,
              46.4422787
            ]
          }
        },
        {
          "type": "Feature",
          "properties": {
            "id": "7397983577",
            "osm_type": "node",
            "lat": 46.4423711,
            "lon": 14.1863472,
            "natural": "stone"
          },
          "geometry": {
            "type": "Point",
            "coordinates": [
              14.1863472,
              46.4423711
            ]
          }
        },
        {
          "type": "Feature",
          "properties": {
            "id": "7397983578",
            "osm_type": "node",
            "lat": 46.4424177,
            "lon": 14.1864223,
            "natural": "stone"
          },
          "geometry": {
            "type": "Point",
            "coordinates": [
              14.1864223,
              46.4424177
            ]
          }
        },
        {
          "type": "Feature",
          "properties": {
            "id": "7397983579",
            "osm_type": "node",
            "lat": 46.4423873,
            "lon": 14.1864989,
            "natural": "stone"
          },
          "geometry": {
            "type": "Point",
            "coordinates": [
              14.1864989,
              46.4423873
            ]
          }
        },
        {
          "type": "Feature",
          "properties": {
            "id": "7397983580",
            "osm_type": "node",
            "lat": 46.4422585,
            "lon": 14.1831022,
            "natural": "stone"
          },
          "geometry": {
            "type": "Point",
            "coordinates": [
              14.1831022,
              46.4422585
            ]
          }
        },
        {
          "type": "Feature",
          "properties": {
            "id": "7397983581",
            "osm_type": "node",
            "lat": 46.4421306,
            "lon": 14.183781,
            "natural": "stone"
          },
          "geometry": {
            "type": "Point",
            "coordinates": [
              14.183781,
              46.4421306
            ]
          }
        },
        {
          "type": "Feature",
          "properties": {
            "id": "7830516130",
            "osm_type": "node",
            "lat": 46.4895161,
            "lon": 14.2666241,
            "natural": "bare_rock",
            "sport": "climbing"
          },
          "geometry": {
            "type": "Point",
            "coordinates": [
              14.2666241,
              46.4895161
            ]
          }
        },
        {
          "type": "Feature",
          "properties": {
            "id": "8544887905",
            "osm_type": "node",
            "lat": 46.5854129,
            "lon": 14.2477197,
            "natural": "sinkhole",
            "sinkhole": "estavelle"
          },
          "geometry": {
            "type": "Point",
            "coordinates": [
              14.2477197,
              46.5854129
            ]
          }
        },
        {
          "type": "Feature",
          "properties": {
            "id": "8762198027",
            "osm_type": "node",
            "lat": 46.459582,
            "lon": 14.0463556,
            "name": "Gola peč",
            "natural": "cliff"
          },
          "geometry": {
            "type": "Point",
            "coordinates": [
              14.0463556,
              46.459582
            ]
          }
        },
        {
          "type": "Feature",
          "properties": {
            "id": "9938888795",
            "osm_type": "node",
            "lat": 46.4160538,
            "lon": 14.1052583,
            "name": "Kamp Perun Lipce - plaža",
            "natural": "beach",
            "surface": "gravel"
          },
          "geometry": {
            "type": "Point",
            "coordinates": [
              14.1052583,
              46.4160538
            ]
          }
        },
        {
          "type": "Feature",
          "properties": {
            "id": "11811256621",
            "osm_type": "node",
            "lat": 46.6200805,
            "lon": 14.2087362,
            "name": "Liegewiese",
            "natural": "beach",
            "surface": "grass"
          },
          "geometry": {
            "type": "Point",
            "coordinates": [
              14.2087362,
              46.6200805
            ]
          }
        },
        {
          "type": "Feature",
          "properties": {
            "id": "12075963378",
            "osm_type": "node",
            "lat": 46.4303178,
            "lon": 14.2601984,
            "natural": "stone",
            "sport": "climbing"
          },
          "geometry": {
            "type": "Point",
            "coordinates": [
              14.2601984,
              46.4303178
            ]
          }
        },
        {
          "type": "Feature",
          "properties": {
            "id": "12551290717",
            "osm_type": "node",
            "lat": 46.5983062,
            "lon": 14.2729164,
            "natural": "shrub"
          },
          "geometry": {
            "type": "Point",
            "coordinates": [
              14.2729164,
              46.5983062
            ]
          }
        },
        {
          "type": "Feature",
          "properties": {
            "id": "12551290718",
            "osm_type": "node",
            "lat": 46.5982872,
            "lon": 14.2729187,
            "natural": "shrub"
          },
          "geometry": {
            "type": "Point",
            "coordinates": [
              14.2729187,
              46.5982872
            ]
          }
        },
        {
          "type": "Feature",
          "properties": {
            "id": "12551290719",
            "osm_type": "node",
            "lat": 46.5982618,
            "lon": 14.2729227,
            "natural": "shrub"
          },
          "geometry": {
            "type": "Point",
            "coordinates": [
              14.2729227,
              46.5982618
            ]
          }
        },
        {
          "type": "Feature",
          "properties": {
            "id": "12551290720",
            "osm_type": "node",
            "lat": 46.5983921,
            "lon": 14.2730554,
            "natural": "shrub"
          },
          "geometry": {
            "type": "Point",
            "coordinates": [
              14.2730554,
              46.5983921
            ]
          }
        }
      ],
      "children": []
    },
    {
      "bbox": {
        "south": 46.372652,
        "west": 14.2994695,
        "north": 46.70320525,
        "east": 15.253173
      },
      "poiCount": 76,
      "leafCount": 0,
      "averagePosition": [
        15.030724792105266,
        46.50640248289474
      ],
      "data": [],
      "children": [
        {
          "bbox": {
            "south": 46.372652,
            "west": 14.2994695,
            "north": 46.537928625000006,
            "east": 14.77632125
          },
          "poiCount": 4,
          "leafCount": 4,
          "averagePosition": [
            14.423639175,
            46.451904575
          ],
          "data": [
            {
              "type": "Feature",
              "properties": {
                "id": "2522553334",
                "osm_type": "node",
                "lat": 46.4534776,
                "lon": 14.4973342,
                "natural": "arch"
              },
              "geometry": {
                "type": "Point",
                "coordinates": [
                  14.4973342,
                  46.4534776
                ]
              }
            },
            {
              "type": "Feature",
              "properties": {
                "id": "7394998760",
                "osm_type": "node",
                "lat": 46.4981024,
                "lon": 14.3022136,
                "natural": "stone"
              },
              "geometry": {
                "type": "Point",
                "coordinates": [
                  14.3022136,
                  46.4981024
                ]
              }
            },
            {
              "type": "Feature",
              "properties": {
                "id": "9770432626",
                "osm_type": "node",
                "lat": 46.402643,
                "lon": 14.3972749,
                "height": "15",
                "name": "Stegovniški slap",
                "name:en": "Stegnovnik Waterfall",
                "natural": "cliff",
                "waterway": "waterfall",
                "wikidata": "Q20189524",
                "wikipedia": "sl:Stegovniški slap"
              },
              "geometry": {
                "type": "Point",
                "coordinates": [
                  14.3972749,
                  46.402643
                ]
              }
            },
            {
              "type": "Feature",
              "properties": {
                "id": "11952519986",
                "osm_type": "node",
                "lat": 46.4533953,
                "lon": 14.497734,
                "natural": "arch"
              },
              "geometry": {
                "type": "Point",
                "coordinates": [
                  14.497734,
                  46.4533953
                ]
              }
            }
          ],
          "children": []
        },
        {
          "bbox": {
            "south": 46.372652,
            "west": 14.77632125,
            "north": 46.537928625000006,
            "east": 15.253173
          },
          "poiCount": 70,
          "leafCount": 0,
          "averagePosition": [
            15.075468937142858,
            46.50586447857143
          ],
          "data": [],
          "children": [
            {
              "bbox": {
                "south": 46.372652,
                "west": 14.77632125,
                "north": 46.455290312500004,
                "east": 15.014747125
              },
              "poiCount": 2,
              "leafCount": 2,
              "averagePosition": [
                14.9160044,
                46.40077975
              ],
              "data": [
                {
                  "type": "Feature",
                  "properties": {
                    "id": "6879566816",
                    "osm_type": "node",
                    "lat": 46.3994665,
                    "lon": 14.9152681,
                    "natural": "sinkhole",
                    "sinkhole": "ponor"
                  },
                  "geometry": {
                    "type": "Point",
                    "coordinates": [
                      14.9152681,
                      46.3994665
                    ]
                  }
                },
                {
                  "type": "Feature",
                  "properties": {
                    "id": "6879566893",
                    "osm_type": "node",
                    "lat": 46.402093,
                    "lon": 14.9167407,
                    "natural": "sinkhole",
                    "sinkhole": "ponor"
                  },
                  "geometry": {
                    "type": "Point",
                    "coordinates": [
                      14.9167407,
                      46.402093
                    ]
                  }
                }
              ],
              "children": []
            },
            {
              "bbox": {
                "south": 46.455290312500004,
                "west": 15.014747125,
                "north": 46.537928625000006,
                "east": 15.253173
              },
              "poiCount": 68,
              "leafCount": 0,
              "averagePosition": [
                15.080159070588236,
                46.50895520588236
              ],
              "data": [],
              "children": [
                {
                  "bbox": {
                    "south": 46.49660946875001,
                    "west": 15.014747125,
                    "north": 46.537928625000006,
                    "east": 15.1339600625
                  },
                  "poiCount": 68,
                  "leafCount": 0,
                  "averagePosition": [
                    15.080159070588236,
                    46.50895520588236
                  ],
                  "data": [],
                  "children": [
                    {
                      "bbox": {
                        "south": 46.49660946875001,
                        "west": 15.07435359375,
                        "north": 46.51726904687501,
                        "east": 15.1339600625
                      },
                      "poiCount": 68,
                      "leafCount": 0,
                      "averagePosition": [
                        15.080159070588236,
                        46.50895520588236
                      ],
                      "data": [],
                      "children": [
                        {
                          "bbox": {
                            "south": 46.49660946875001,
                            "west": 15.07435359375,
                            "north": 46.506939257812505,
                            "east": 15.104156828125
                          },
                          "poiCount": 27,
                          "leafCount": 27,
                          "averagePosition": [
                            15.081026714814815,
                            46.50657051481481
                          ],
                          "data": [
                            {
                              "type": "Feature",
                              "properties": {
                                "id": "12582854393",
                                "osm_type": "node",
                                "lat": 46.5066099,
                                "lon": 15.0803971,
                                "natural": "shrub"
                              },
                              "geometry": {
                                "type": "Point",
                                "coordinates": [
                                  15.0803971,
                                  46.5066099
                                ]
                              }
                            },
                            {
                              "type": "Feature",
                              "properties": {
                                "id": "12582854394",
                                "osm_type": "node",
                                "lat": 46.5065655,
                                "lon": 15.0804469,
                                "natural": "shrub"
                              },
                              "geometry": {
                                "type": "Point",
                                "coordinates": [
                                  15.0804469,
                                  46.5065655
                                ]
                              }
                            },
                            {
                              "type": "Feature",
                              "properties": {
                                "id": "12582854395",
                                "osm_type": "node",
                                "lat": 46.5065274,
                                "lon": 15.0804942,
                                "natural": "shrub"
                              },
                              "geometry": {
                                "type": "Point",
                                "coordinates": [
                                  15.0804942,
                                  46.5065274
                                ]
                              }
                            },
                            {
                              "type": "Feature",
                              "properties": {
                                "id": "12582854396",
                                "osm_type": "node",
                                "lat": 46.5065837,
                                "lon": 15.0808256,
                                "natural": "shrub"
                              },
                              "geometry": {
                                "type": "Point",
                                "coordinates": [
                                  15.0808256,
                                  46.5065837
                                ]
                              }
                            },
                            {
                              "type": "Feature",
                              "properties": {
                                "id": "12582854397",
                                "osm_type": "node",
                                "lat": 46.5065532,
                                "lon": 15.0808613,
                                "natural": "shrub"
                              },
                              "geometry": {
                                "type": "Point",
                                "coordinates": [
                                  15.0808613,
                                  46.5065532
                                ]
                              }
                            },
                            {
                              "type": "Feature",
                              "properties": {
                                "id": "12582854398",
                                "osm_type": "node",
                                "lat": 46.5066268,
                                "lon": 15.0807666,
                                "natural": "shrub"
                              },
                              "geometry": {
                                "type": "Point",
                                "coordinates": [
                                  15.0807666,
                                  46.5066268
                                ]
                              }
                            },
                            {
                              "type": "Feature",
                              "properties": {
                                "id": "12582854399",
                                "osm_type": "node",
                                "lat": 46.5065634,
                                "lon": 15.0805969,
                                "natural": "shrub"
                              },
                              "geometry": {
                                "type": "Point",
                                "coordinates": [
                                  15.0805969,
                                  46.5065634
                                ]
                              }
                            },
                            {
                              "type": "Feature",
                              "properties": {
                                "id": "12582857199",
                                "osm_type": "node",
                                "lat": 46.5065312,
                                "lon": 15.081081,
                                "natural": "shrub"
                              },
                              "geometry": {
                                "type": "Point",
                                "coordinates": [
                                  15.081081,
                                  46.5065312
                                ]
                              }
                            },
                            {
                              "type": "Feature",
                              "properties": {
                                "id": "12582857200",
                                "osm_type": "node",
                                "lat": 46.5065236,
                                "lon": 15.0810996,
                                "natural": "shrub"
                              },
                              "geometry": {
                                "type": "Point",
                                "coordinates": [
                                  15.0810996,
                                  46.5065236
                                ]
                              }
                            },
                            {
                              "type": "Feature",
                              "properties": {
                                "id": "12582860701",
                                "osm_type": "node",
                                "lat": 46.5065105,
                                "lon": 15.0810795,
                                "natural": "shrub"
                              },
                              "geometry": {
                                "type": "Point",
                                "coordinates": [
                                  15.0810795,
                                  46.5065105
                                ]
                              }
                            },
                            {
                              "type": "Feature",
                              "properties": {
                                "id": "12582860702",
                                "osm_type": "node",
                                "lat": 46.5064984,
                                "lon": 15.0810654,
                                "natural": "shrub"
                              },
                              "geometry": {
                                "type": "Point",
                                "coordinates": [
                                  15.0810654,
                                  46.5064984
                                ]
                              }
                            },
                            {
                              "type": "Feature",
                              "properties": {
                                "id": "12582860703",
                                "osm_type": "node",
                                "lat": 46.5065032,
                                "lon": 15.0811031,
                                "natural": "shrub"
                              },
                              "geometry": {
                                "type": "Point",
                                "coordinates": [
                                  15.0811031,
                                  46.5065032
                                ]
                              }
                            },
                            {
                              "type": "Feature",
                              "properties": {
                                "id": "12582860704",
                                "osm_type": "node",
                                "lat": 46.5064942,
                                "lon": 15.081086,
                                "natural": "shrub"
                              },
                              "geometry": {
                                "type": "Point",
                                "coordinates": [
                                  15.081086,
                                  46.5064942
                                ]
                              }
                            },
                            {
                              "type": "Feature",
                              "properties": {
                                "id": "12582860705",
                                "osm_type": "node",
                                "lat": 46.506479,
                                "lon": 15.0811021,
                                "natural": "shrub"
                              },
                              "geometry": {
                                "type": "Point",
                                "coordinates": [
                                  15.0811021,
                                  46.506479
                                ]
                              }
                            },
                            {
                              "type": "Feature",
                              "properties": {
                                "id": "12582860706",
                                "osm_type": "node",
                                "lat": 46.5064665,
                                "lon": 15.0811851,
                                "natural": "shrub"
                              },
                              "geometry": {
                                "type": "Point",
                                "coordinates": [
                                  15.0811851,
                                  46.5064665
                                ]
                              }
                            },
                            {
                              "type": "Feature",
                              "properties": {
                                "id": "12582860707",
                                "osm_type": "node",
                                "lat": 46.5064655,
                                "lon": 15.0812167,
                                "natural": "shrub"
                              },
                              "geometry": {
                                "type": "Point",
                                "coordinates": [
                                  15.0812167,
                                  46.5064655
                                ]
                              }
                            },
                            {
                              "type": "Feature",
                              "properties": {
                                "id": "12582860708",
                                "osm_type": "node",
                                "lat": 46.5064503,
                                "lon": 15.0812454,
                                "natural": "shrub"
                              },
                              "geometry": {
                                "type": "Point",
                                "coordinates": [
                                  15.0812454,
                                  46.5064503
                                ]
                              }
                            },
                            {
                              "type": "Feature",
                              "properties": {
                                "id": "12582860709",
                                "osm_type": "node",
                                "lat": 46.5064433,
                                "lon": 15.081173,
                                "natural": "shrub"
                              },
                              "geometry": {
                                "type": "Point",
                                "coordinates": [
                                  15.081173,
                                  46.5064433
                                ]
                              }
                            },
                            {
                              "type": "Feature",
                              "properties": {
                                "id": "12582860710",
                                "osm_type": "node",
                                "lat": 46.5064212,
                                "lon": 15.0811846,
                                "natural": "shrub"
                              },
                              "geometry": {
                                "type": "Point",
                                "coordinates": [
                                  15.0811846,
                                  46.5064212
                                ]
                              }
                            },
                            {
                              "type": "Feature",
                              "properties": {
                                "id": "12582860711",
                                "osm_type": "node",
                                "lat": 46.5066648,
                                "lon": 15.0813057,
                                "natural": "shrub"
                              },
                              "geometry": {
                                "type": "Point",
                                "coordinates": [
                                  15.0813057,
                                  46.5066648
                                ]
                              }
                            },
                            {
                              "type": "Feature",
                              "properties": {
                                "id": "12582860712",
                                "osm_type": "node",
                                "lat": 46.5066509,
                                "lon": 15.0813334,
                                "natural": "shrub"
                              },
                              "geometry": {
                                "type": "Point",
                                "coordinates": [
                                  15.0813334,
                                  46.5066509
                                ]
                              }
                            },
                            {
                              "type": "Feature",
                              "properties": {
                                "id": "12582860713",
                                "osm_type": "node",
                                "lat": 46.5066624,
                                "lon": 15.0813459,
                                "natural": "shrub"
                              },
                              "geometry": {
                                "type": "Point",
                                "coordinates": [
                                  15.0813459,
                                  46.5066624
                                ]
                              }
                            },
                            {
                              "type": "Feature",
                              "properties": {
                                "id": "12582860714",
                                "osm_type": "node",
                                "lat": 46.5066696,
                                "lon": 15.0813248,
                                "natural": "shrub"
                              },
                              "geometry": {
                                "type": "Point",
                                "coordinates": [
                                  15.0813248,
                                  46.5066696
                                ]
                              }
                            },
                            {
                              "type": "Feature",
                              "properties": {
                                "id": "12582860715",
                                "osm_type": "node",
                                "lat": 46.5066914,
                                "lon": 15.0813203,
                                "natural": "shrub"
                              },
                              "geometry": {
                                "type": "Point",
                                "coordinates": [
                                  15.0813203,
                                  46.5066914
                                ]
                              }
                            },
                            {
                              "type": "Feature",
                              "properties": {
                                "id": "12582860716",
                                "osm_type": "node",
                                "lat": 46.5067046,
                                "lon": 15.0809226,
                                "natural": "shrub"
                              },
                              "geometry": {
                                "type": "Point",
                                "coordinates": [
                                  15.0809226,
                                  46.5067046
                                ]
                              }
                            },
                            {
                              "type": "Feature",
                              "properties": {
                                "id": "12582860717",
                                "osm_type": "node",
                                "lat": 46.5067219,
                                "lon": 15.0809523,
                                "natural": "shrub"
                              },
                              "geometry": {
                                "type": "Point",
                                "coordinates": [
                                  15.0809523,
                                  46.5067219
                                ]
                              }
                            },
                            {
                              "type": "Feature",
                              "properties": {
                                "id": "12582860718",
                                "osm_type": "node",
                                "lat": 46.5068215,
                                "lon": 15.0812062,
                                "natural": "shrub"
                              },
                              "geometry": {
                                "type": "Point",
                                "coordinates": [
                                  15.0812062,
                                  46.5068215
                                ]
                              }
                            }
                          ],
                          "children": []
                        },
                        {
                          "bbox": {
                            "south": 46.506939257812505,
                            "west": 15.07435359375,
                            "north": 46.51726904687501,
                            "east": 15.104156828125
                          },
                          "poiCount": 41,
                          "leafCount": 41,
                          "averagePosition": [
                            15.079587695121951,
                            46.510525612195124
                          ],
                          "data": [
                            {
                              "type": "Feature",
                              "properties": {
                                "id": "12581986833",
                                "osm_type": "node",
                                "lat": 46.5097715,
                                "lon": 15.0778537,
                                "natural": "shrub"
                              },
                              "geometry": {
                                "type": "Point",
                                "coordinates": [
                                  15.0778537,
                                  46.5097715
                                ]
                              }
                            },
                            {
                              "type": "Feature",
                              "properties": {
                                "id": "12581986834",
                                "osm_type": "node",
                                "lat": 46.5097609,
                                "lon": 15.0779196,
                                "natural": "shrub"
                              },
                              "geometry": {
                                "type": "Point",
                                "coordinates": [
                                  15.0779196,
                                  46.5097609
                                ]
                              }
                            },
                            {
                              "type": "Feature",
                              "properties": {
                                "id": "12582031702",
                                "osm_type": "node",
                                "lat": 46.5106012,
                                "lon": 15.0808599,
                                "natural": "shrub"
                              },
                              "geometry": {
                                "type": "Point",
                                "coordinates": [
                                  15.0808599,
                                  46.5106012
                                ]
                              }
                            },
                            {
                              "type": "Feature",
                              "properties": {
                                "id": "12582031703",
                                "osm_type": "node",
                                "lat": 46.5105489,
                                "lon": 15.0809276,
                                "natural": "shrub"
                              },
                              "geometry": {
                                "type": "Point",
                                "coordinates": [
                                  15.0809276,
                                  46.5105489
                                ]
                              }
                            },
                            {
                              "type": "Feature",
                              "properties": {
                                "id": "12582064161",
                                "osm_type": "node",
                                "lat": 46.5073192,
                                "lon": 15.0785225,
                                "natural": "shrub"
                              },
                              "geometry": {
                                "type": "Point",
                                "coordinates": [
                                  15.0785225,
                                  46.5073192
                                ]
                              }
                            },
                            {
                              "type": "Feature",
                              "properties": {
                                "id": "12582064162",
                                "osm_type": "node",
                                "lat": 46.5072505,
                                "lon": 15.0786934,
                                "natural": "shrub"
                              },
                              "geometry": {
                                "type": "Point",
                                "coordinates": [
                                  15.0786934,
                                  46.5072505
                                ]
                              }
                            },
                            {
                              "type": "Feature",
                              "properties": {
                                "id": "12582064163",
                                "osm_type": "node",
                                "lat": 46.5072357,
                                "lon": 15.0787148,
                                "natural": "shrub"
                              },
                              "geometry": {
                                "type": "Point",
                                "coordinates": [
                                  15.0787148,
                                  46.5072357
                                ]
                              }
                            },
                            {
                              "type": "Feature",
                              "properties": {
                                "id": "12582064164",
                                "osm_type": "node",
                                "lat": 46.5072091,
                                "lon": 15.0787691,
                                "natural": "shrub"
                              },
                              "geometry": {
                                "type": "Point",
                                "coordinates": [
                                  15.0787691,
                                  46.5072091
                                ]
                              }
                            },
                            {
                              "type": "Feature",
                              "properties": {
                                "id": "12582064165",
                                "osm_type": "node",
                                "lat": 46.5073909,
                                "lon": 15.0792606,
                                "natural": "shrub"
                              },
                              "geometry": {
                                "type": "Point",
                                "coordinates": [
                                  15.0792606,
                                  46.5073909
                                ]
                              }
                            },
                            {
                              "type": "Feature",
                              "properties": {
                                "id": "12582064166",
                                "osm_type": "node",
                                "lat": 46.5074233,
                                "lon": 15.0792534,
                                "natural": "shrub"
                              },
                              "geometry": {
                                "type": "Point",
                                "coordinates": [
                                  15.0792534,
                                  46.5074233
                                ]
                              }
                            },
                            {
                              "type": "Feature",
                              "properties": {
                                "id": "12582064167",
                                "osm_type": "node",
                                "lat": 46.5074563,
                                "lon": 15.0792478,
                                "natural": "shrub"
                              },
                              "geometry": {
                                "type": "Point",
                                "coordinates": [
                                  15.0792478,
                                  46.5074563
                                ]
                              }
                            },
                            {
                              "type": "Feature",
                              "properties": {
                                "id": "12582064168",
                                "osm_type": "node",
                                "lat": 46.5074838,
                                "lon": 15.0792454,
                                "natural": "shrub"
                              },
                              "geometry": {
                                "type": "Point",
                                "coordinates": [
                                  15.0792454,
                                  46.5074838
                                ]
                              }
                            },
                            {
                              "type": "Feature",
                              "properties": {
                                "id": "12582064535",
                                "osm_type": "node",
                                "lat": 46.5098625,
                                "lon": 15.0822779,
                                "natural": "shrub"
                              },
                              "geometry": {
                                "type": "Point",
                                "coordinates": [
                                  15.0822779,
                                  46.5098625
                                ]
                              }
                            },
                            {
                              "type": "Feature",
                              "properties": {
                                "id": "12582064536",
                                "osm_type": "node",
                                "lat": 46.5098883,
                                "lon": 15.0822654,
                                "natural": "shrub"
                              },
                              "geometry": {
                                "type": "Point",
                                "coordinates": [
                                  15.0822654,
                                  46.5098883
                                ]
                              }
                            },
                            {
                              "type": "Feature",
                              "properties": {
                                "id": "12582064537",
                                "osm_type": "node",
                                "lat": 46.509874,
                                "lon": 15.0821961,
                                "natural": "shrub"
                              },
                              "geometry": {
                                "type": "Point",
                                "coordinates": [
                                  15.0821961,
                                  46.509874
                                ]
                              }
                            },
                            {
                              "type": "Feature",
                              "properties": {
                                "id": "12582064538",
                                "osm_type": "node",
                                "lat": 46.5100486,
                                "lon": 15.0821822,
                                "natural": "shrub"
                              },
                              "geometry": {
                                "type": "Point",
                                "coordinates": [
                                  15.0821822,
                                  46.5100486
                                ]
                              }
                            },
                            {
                              "type": "Feature",
                              "properties": {
                                "id": "12582064539",
                                "osm_type": "node",
                                "lat": 46.5100944,
                                "lon": 15.0821614,
                                "natural": "shrub"
                              },
                              "geometry": {
                                "type": "Point",
                                "coordinates": [
                                  15.0821614,
                                  46.5100944
                                ]
                              }
                            },
                            {
                              "type": "Feature",
                              "properties": {
                                "id": "12582064540",
                                "osm_type": "node",
                                "lat": 46.5102661,
                                "lon": 15.0821462,
                                "natural": "shrub"
                              },
                              "geometry": {
                                "type": "Point",
                                "coordinates": [
                                  15.0821462,
                                  46.5102661
                                ]
                              }
                            },
                            {
                              "type": "Feature",
                              "properties": {
                                "id": "12582064541",
                                "osm_type": "node",
                                "lat": 46.5096087,
                                "lon": 15.0822405,
                                "natural": "shrub"
                              },
                              "geometry": {
                                "type": "Point",
                                "coordinates": [
                                  15.0822405,
                                  46.5096087
                                ]
                              }
                            },
                            {
                              "type": "Feature",
                              "properties": {
                                "id": "12582064542",
                                "osm_type": "node",
                                "lat": 46.5096707,
                                "lon": 15.082271,
                                "natural": "shrub"
                              },
                              "geometry": {
                                "type": "Point",
                                "coordinates": [
                                  15.082271,
                                  46.5096707
                                ]
                              }
                            },
                            {
                              "type": "Feature",
                              "properties": {
                                "id": "12582064543",
                                "osm_type": "node",
                                "lat": 46.5095104,
                                "lon": 15.0824068,
                                "natural": "shrub"
                              },
                              "geometry": {
                                "type": "Point",
                                "coordinates": [
                                  15.0824068,
                                  46.5095104
                                ]
                              }
                            },
                            {
                              "type": "Feature",
                              "properties": {
                                "id": "12582110218",
                                "osm_type": "node",
                                "lat": 46.5120374,
                                "lon": 15.0821429,
                                "natural": "shrub"
                              },
                              "geometry": {
                                "type": "Point",
                                "coordinates": [
                                  15.0821429,
                                  46.5120374
                                ]
                              }
                            },
                            {
                              "type": "Feature",
                              "properties": {
                                "id": "12585012845",
                                "osm_type": "node",
                                "lat": 46.5120899,
                                "lon": 15.0782611,
                                "natural": "shrub"
                              },
                              "geometry": {
                                "type": "Point",
                                "coordinates": [
                                  15.0782611,
                                  46.5120899
                                ]
                              }
                            },
                            {
                              "type": "Feature",
                              "properties": {
                                "id": "12585012846",
                                "osm_type": "node",
                                "lat": 46.5120867,
                                "lon": 15.078438,
                                "natural": "shrub"
                              },
                              "geometry": {
                                "type": "Point",
                                "coordinates": [
                                  15.078438,
                                  46.5120867
                                ]
                              }
                            },
                            {
                              "type": "Feature",
                              "properties": {
                                "id": "12585012847",
                                "osm_type": "node",
                                "lat": 46.5120836,
                                "lon": 15.0785528,
                                "natural": "shrub"
                              },
                              "geometry": {
                                "type": "Point",
                                "coordinates": [
                                  15.0785528,
                                  46.5120836
                                ]
                              }
                            },
                            {
                              "type": "Feature",
                              "properties": {
                                "id": "12585012848",
                                "osm_type": "node",
                                "lat": 46.5120638,
                                "lon": 15.0786228,
                                "natural": "shrub"
                              },
                              "geometry": {
                                "type": "Point",
                                "coordinates": [
                                  15.0786228,
                                  46.5120638
                                ]
                              }
                            },
                            {
                              "type": "Feature",
                              "properties": {
                                "id": "12585012849",
                                "osm_type": "node",
                                "lat": 46.5125381,
                                "lon": 15.0779734,
                                "natural": "shrub"
                              },
                              "geometry": {
                                "type": "Point",
                                "coordinates": [
                                  15.0779734,
                                  46.5125381
                                ]
                              }
                            },
                            {
                              "type": "Feature",
                              "properties": {
                                "id": "12585012850",
                                "osm_type": "node",
                                "lat": 46.5123721,
                                "lon": 15.0769371,
                                "natural": "shrub"
                              },
                              "geometry": {
                                "type": "Point",
                                "coordinates": [
                                  15.0769371,
                                  46.5123721
                                ]
                              }
                            },
                            {
                              "type": "Feature",
                              "properties": {
                                "id": "12585012851",
                                "osm_type": "node",
                                "lat": 46.512001,
                                "lon": 15.0786861,
                                "natural": "shrub"
                              },
                              "geometry": {
                                "type": "Point",
                                "coordinates": [
                                  15.0786861,
                                  46.512001
                                ]
                              }
                            },
                            {
                              "type": "Feature",
                              "properties": {
                                "id": "12585012852",
                                "osm_type": "node",
                                "lat": 46.5122714,
                                "lon": 15.0787536,
                                "natural": "shrub"
                              },
                              "geometry": {
                                "type": "Point",
                                "coordinates": [
                                  15.0787536,
                                  46.5122714
                                ]
                              }
                            },
                            {
                              "type": "Feature",
                              "properties": {
                                "id": "12585012853",
                                "osm_type": "node",
                                "lat": 46.5122917,
                                "lon": 15.0787389,
                                "natural": "shrub"
                              },
                              "geometry": {
                                "type": "Point",
                                "coordinates": [
                                  15.0787389,
                                  46.5122917
                                ]
                              }
                            },
                            {
                              "type": "Feature",
                              "properties": {
                                "id": "12585012854",
                                "osm_type": "node",
                                "lat": 46.5123167,
                                "lon": 15.0787242,
                                "natural": "shrub"
                              },
                              "geometry": {
                                "type": "Point",
                                "coordinates": [
                                  15.0787242,
                                  46.5123167
                                ]
                              }
                            },
                            {
                              "type": "Feature",
                              "properties": {
                                "id": "12585012855",
                                "osm_type": "node",
                                "lat": 46.5123268,
                                "lon": 15.07868,
                                "natural": "shrub"
                              },
                              "geometry": {
                                "type": "Point",
                                "coordinates": [
                                  15.07868,
                                  46.5123268
                                ]
                              }
                            },
                            {
                              "type": "Feature",
                              "properties": {
                                "id": "12585012856",
                                "osm_type": "node",
                                "lat": 46.5123339,
                                "lon": 15.0786082,
                                "natural": "shrub"
                              },
                              "geometry": {
                                "type": "Point",
                                "coordinates": [
                                  15.0786082,
                                  46.5123339
                                ]
                              }
                            },
                            {
                              "type": "Feature",
                              "properties": {
                                "id": "12585012860",
                                "osm_type": "node",
                                "lat": 46.51197,
                                "lon": 15.079085,
                                "natural": "shrub"
                              },
                              "geometry": {
                                "type": "Point",
                                "coordinates": [
                                  15.079085,
                                  46.51197
                                ]
                              }
                            },
                            {
                              "type": "Feature",
                              "properties": {
                                "id": "12585012861",
                                "osm_type": "node",
                                "lat": 46.5119742,
                                "lon": 15.0791603,
                                "natural": "shrub"
                              },
                              "geometry": {
                                "type": "Point",
                                "coordinates": [
                                  15.0791603,
                                  46.5119742
                                ]
                              }
                            },
                            {
                              "type": "Feature",
                              "properties": {
                                "id": "12585012862",
                                "osm_type": "node",
                                "lat": 46.5119569,
                                "lon": 15.0789016,
                                "natural": "shrub"
                              },
                              "geometry": {
                                "type": "Point",
                                "coordinates": [
                                  15.0789016,
                                  46.5119569
                                ]
                              }
                            },
                            {
                              "type": "Feature",
                              "properties": {
                                "id": "12585012863",
                                "osm_type": "node",
                                "lat": 46.512051,
                                "lon": 15.0791638,
                                "natural": "shrub"
                              },
                              "geometry": {
                                "type": "Point",
                                "coordinates": [
                                  15.0791638,
                                  46.512051
                                ]
                              }
                            },
                            {
                              "type": "Feature",
                              "properties": {
                                "id": "12585012864",
                                "osm_type": "node",
                                "lat": 46.5121871,
                                "lon": 15.0781345,
                                "natural": "shrub"
                              },
                              "geometry": {
                                "type": "Point",
                                "coordinates": [
                                  15.0781345,
                                  46.5121871
                                ]
                              }
                            },
                            {
                              "type": "Feature",
                              "properties": {
                                "id": "12585012865",
                                "osm_type": "node",
                                "lat": 46.5121717,
                                "lon": 15.0780583,
                                "natural": "shrub"
                              },
                              "geometry": {
                                "type": "Point",
                                "coordinates": [
                                  15.0780583,
                                  46.5121717
                                ]
                              }
                            },
                            {
                              "type": "Feature",
                              "properties": {
                                "id": "12585012866",
                                "osm_type": "node",
                                "lat": 46.5121511,
                                "lon": 15.0780576,
                                "natural": "shrub"
                              },
                              "geometry": {
                                "type": "Point",
                                "coordinates": [
                                  15.0780576,
                                  46.5121511
                                ]
                              }
                            }
                          ],
                          "children": []
                        }
                      ]
                    }
                  ]
                }
              ]
            }
          ]
        },
        {
          "bbox": {
            "south": 46.537928625000006,
            "west": 14.2994695,
            "north": 46.70320525,
            "east": 14.77632125
          },
          "poiCount": 1,
          "leafCount": 1,
          "averagePosition": [
            14.3193369,
            46.6199107
          ],
          "data": [
            {
              "type": "Feature",
              "properties": {
                "id": "8805343369",
                "osm_type": "node",
                "lat": 46.6199107,
                "lon": 14.3193369,
                "natural": "shrub"
              },
              "geometry": {
                "type": "Point",
                "coordinates": [
                  14.3193369,
                  46.6199107
                ]
              }
            }
          ],
          "children": []
        },
        {
          "bbox": {
            "south": 46.537928625000006,
            "west": 14.77632125,
            "north": 46.70320525,
            "east": 15.253173
          },
          "poiCount": 1,
          "leafCount": 1,
          "averagePosition": [
            15.038365,
            46.6485462
          ],
          "data": [
            {
              "type": "Feature",
              "properties": {
                "id": "1445580481",
                "osm_type": "node",
                "lat": 46.6485462,
                "lon": 15.038365,
                "name": "Volčji kamen",
                "natural": "stone"
              },
              "geometry": {
                "type": "Point",
                "coordinates": [
                  15.038365,
                  46.6485462
                ]
              }
            }
          ],
          "children": []
        }
      ]
    },
    {
      "bbox": {
        "south": 46.70320525,
        "west": 13.345766,
        "north": 47.033758500000005,
        "east": 14.2994695
      },
      "poiCount": 20,
      "leafCount": 20,
      "averagePosition": [
        13.66774129,
        46.829904285
      ],
      "data": [
        {
          "type": "Feature",
          "properties": {
            "id": "4038513154",
            "osm_type": "node",
            "lat": 46.9067173,
            "lon": 13.4302504,
            "name": "Serzenmoos",
            "natural": "wetland"
          },
          "geometry": {
            "type": "Point",
            "coordinates": [
              13.4302504,
              46.9067173
            ]
          }
        },
        {
          "type": "Feature",
          "properties": {
            "id": "4929953335",
            "osm_type": "node",
            "lat": 47.0032613,
            "lon": 13.447951,
            "climbing:boulder": "yes",
            "name": "Meilenstein",
            "natural": "stone",
            "protected": "no",
            "sport": "climbing"
          },
          "geometry": {
            "type": "Point",
            "coordinates": [
              13.447951,
              47.0032613
            ]
          }
        },
        {
          "type": "Feature",
          "properties": {
            "id": "4929963800",
            "osm_type": "node",
            "lat": 47.0035903,
            "lon": 13.4464628,
            "climbing:boulder": "yes",
            "name": "Alligator",
            "natural": "stone",
            "sport": "climbing"
          },
          "geometry": {
            "type": "Point",
            "coordinates": [
              13.4464628,
              47.0035903
            ]
          }
        },
        {
          "type": "Feature",
          "properties": {
            "id": "9126371382",
            "osm_type": "node",
            "lat": 46.9723769,
            "lon": 13.944698,
            "natural": "sinkhole"
          },
          "geometry": {
            "type": "Point",
            "coordinates": [
              13.944698,
              46.9723769
            ]
          }
        },
        {
          "type": "Feature",
          "properties": {
            "id": "9126371390",
            "osm_type": "node",
            "lat": 46.9718915,
            "lon": 13.9460327,
            "natural": "sinkhole"
          },
          "geometry": {
            "type": "Point",
            "coordinates": [
              13.9460327,
              46.9718915
            ]
          }
        },
        {
          "type": "Feature",
          "properties": {
            "id": "5816667986",
            "osm_type": "node",
            "lat": 46.8141276,
            "lon": 13.5286108,
            "description": "Freier Seezugang, Kostenlos",
            "leisure": "bathing_place",
            "name": "Freier Seezugang Klauberpark",
            "natural": "beach",
            "sport": "swimming",
            "surface": "sand"
          },
          "geometry": {
            "type": "Point",
            "coordinates": [
              13.5286108,
              46.8141276
            ]
          }
        },
        {
          "type": "Feature",
          "properties": {
            "id": "8936660578",
            "osm_type": "node",
            "lat": 46.8008245,
            "lon": 13.5204322,
            "natural": "stone"
          },
          "geometry": {
            "type": "Point",
            "coordinates": [
              13.5204322,
              46.8008245
            ]
          }
        },
        {
          "type": "Feature",
          "properties": {
            "id": "9870392767",
            "osm_type": "node",
            "lat": 46.7603341,
            "lon": 13.4749594,
            "height": "1812",
            "name": "Heidentor",
            "natural": "arch"
          },
          "geometry": {
            "type": "Point",
            "coordinates": [
              13.4749594,
              46.7603341
            ]
          }
        },
        {
          "type": "Feature",
          "properties": {
            "id": "4426202751",
            "osm_type": "node",
            "lat": 46.764336,
            "lon": 13.6243771,
            "description": "Der Badeplatz „Bank im See“ bietet ein einzigartiges Panorama. Als besondere Attraktion\nbietet der Seezugang ein vom Künstler Thomas Györi entworfene eischalenförmige Sitzgelegenheit\n„Bank im See“ im Wasser.",
            "leisure": "bathing_place",
            "name": "Freier Seezugang Badeplatz „Bank im See“",
            "natural": "beach",
            "sport": "swimming",
            "website": "https://gis.ktn.gv.at/leaflet/Fotoseezu/bad_21.pdf"
          },
          "geometry": {
            "type": "Point",
            "coordinates": [
              13.6243771,
              46.764336
            ]
          }
        },
        {
          "type": "Feature",
          "properties": {
            "id": "6882531706",
            "osm_type": "node",
            "lat": 46.766995,
            "lon": 13.7508797,
            "description": "Mit Bank und ein bisschen Wiese",
            "name": "Badestelle",
            "natural": "beach"
          },
          "geometry": {
            "type": "Point",
            "coordinates": [
              13.7508797,
              46.766995
            ]
          }
        },
        {
          "type": "Feature",
          "properties": {
            "id": "8048703473",
            "osm_type": "node",
            "lat": 46.8202778,
            "lon": 13.5394607,
            "name": "Quelle Wassergenossenschaft Sanksiedlung Ost",
            "natural": "wetland"
          },
          "geometry": {
            "type": "Point",
            "coordinates": [
              13.5394607,
              46.8202778
            ]
          }
        },
        {
          "type": "Feature",
          "properties": {
            "id": "11398877304",
            "osm_type": "node",
            "lat": 46.7950259,
            "lon": 13.5654626,
            "leisure": "bathing_place",
            "name": "Freier Seezugang Millstätter See bei Spittal an der Drau, Großegg",
            "natural": "beach",
            "sport": "swimming"
          },
          "geometry": {
            "type": "Point",
            "coordinates": [
              13.5654626,
              46.7950259
            ]
          }
        },
        {
          "type": "Feature",
          "properties": {
            "id": "11398920252",
            "osm_type": "node",
            "lat": 46.810864,
            "lon": 13.5481213,
            "leisure": "bathing_place",
            "name": "Freier Seezugang Millstättersee - Parkplatz Tschall",
            "natural": "beach",
            "sport": "swimming",
            "website": "https://gis.ktn.gv.at/leaflet/Fotoseezu/bad_20.pdf"
          },
          "geometry": {
            "type": "Point",
            "coordinates": [
              13.5481213,
              46.810864
            ]
          }
        },
        {
          "type": "Feature",
          "properties": {
            "id": "11398924461",
            "osm_type": "node",
            "lat": 46.7930277,
            "lon": 13.6056189,
            "description": "Info: Ein langgezogener ebener Wiesenbereich liegt direkt am \"Millstätter See Radweg\" (R2B) zwischen Millstatt und Dellach. Ins Wasser gelangt man über eine kleine Böschung, Steine erleichtern den Zugang in den See.",
            "leisure": "bathing_place",
            "lifeguard": "no",
            "name": "Freier Seezugang Millstättersee nahe Schiffsanlegestelle Dellach-Sappl",
            "natural": "beach",
            "sport": "swimming",
            "supervised": "no",
            "surface": "grass",
            "website": "https://gis.ktn.gv.at/leaflet/Fotoseezu/bad_4.pdf"
          },
          "geometry": {
            "type": "Point",
            "coordinates": [
              13.6056189,
              46.7930277
            ]
          }
        },
        {
          "type": "Feature",
          "properties": {
            "id": "11398963962",
            "osm_type": "node",
            "lat": 46.8616383,
            "lon": 13.8297798,
            "description": "Höchster freie Seezugang Kärntens. Wunderschön gelegen, lädt der Hochgebirgssee zu einer erfrischenden Abkühlung umringt vom\nwunderschönen Bergpanorama der Gurktaler Alpen.",
            "leisure": "bathing_place",
            "name": "Freier Seezugang Falkertsee",
            "natural": "beach",
            "sport": "swimming",
            "surface": "grass",
            "website": "https://gis.ktn.gv.at/leaflet/Fotoseezu/bad_333.pdf"
          },
          "geometry": {
            "type": "Point",
            "coordinates": [
              13.8297798,
              46.8616383
            ]
          }
        },
        {
          "type": "Feature",
          "properties": {
            "id": "11398974279",
            "osm_type": "node",
            "lat": 46.7738177,
            "lon": 13.7525598,
            "leisure": "bathing_place",
            "name": "Freier Seezugang Feldsee (Brennsee) - An der Seestraße",
            "natural": "beach",
            "sport": "swimming",
            "website": "https://gis.ktn.gv.at/leaflet/Fotoseezu/bad_7.pdf"
          },
          "geometry": {
            "type": "Point",
            "coordinates": [
              13.7525598,
              46.7738177
            ]
          }
        },
        {
          "type": "Feature",
          "properties": {
            "id": "11398976275",
            "osm_type": "node",
            "lat": 46.7513057,
            "lon": 13.7643746,
            "description": "Wunderbarer natürlicher Schatten auf Grund\nhochwüchsiger Laubbäume macht diesen freien Seezugang zu einem Badeparadies.",
            "leisure": "bathing_place",
            "name": "Freier Seezugang Afritzer See Am Nordufer",
            "natural": "beach",
            "sport": "swimming",
            "surface": "grass",
            "website": "https://gis.ktn.gv.at/leaflet/Fotoseezu/bad_6.pdf"
          },
          "geometry": {
            "type": "Point",
            "coordinates": [
              13.7643746,
              46.7513057
            ]
          }
        },
        {
          "type": "Feature",
          "properties": {
            "id": "11399023112",
            "osm_type": "node",
            "lat": 46.7381067,
            "lon": 13.7707692,
            "description": "Der freie Seezugang in Afritz am See lädt mit einzigartigem Panorama zur schnellen Abkühlung im\nschönen Gegendtal. Der See liegt inmitten der Nockbergen auf einer Höhe von 752m zwischen dem\nWöllaner Nock und dem Mirnock.",
            "leisure": "bathing_place",
            "name": "Freier Seezugang Afritz am See",
            "natural": "beach",
            "sport": "swimming",
            "website": "https://gis.ktn.gv.at/leaflet/Fotoseezu/bad_28.pdf"
          },
          "geometry": {
            "type": "Point",
            "coordinates": [
              13.7707692,
              46.7381067
            ]
          }
        },
        {
          "type": "Feature",
          "properties": {
            "id": "12015153521",
            "osm_type": "node",
            "lat": 46.7747362,
            "lon": 13.6398436,
            "description": "Hoteleigene Liegewiese am See",
            "name": "Privatstrand \"Hotel zur Post\"",
            "natural": "beach",
            "website": "https://hotelzurpost.co.at/"
          },
          "geometry": {
            "type": "Point",
            "coordinates": [
              13.6398436,
              46.7747362
            ]
          }
        },
        {
          "type": "Feature",
          "properties": {
            "id": "10230712776",
            "osm_type": "node",
            "lat": 46.7148312,
            "lon": 14.2241812,
            "height": "4",
            "name": "Miniklippe auf Privatgrund",
            "natural": "cliff"
          },
          "geometry": {
            "type": "Point",
            "coordinates": [
              14.2241812,
              46.7148312
            ]
          }
        }
      ],
      "children": []
    },
    {
      "bbox": {
        "south": 46.70320525,
        "west": 14.2994695,
        "north": 47.033758500000005,
        "east": 15.253173
      },
      "poiCount": 14,
      "leafCount": 14,
      "averagePosition": [
        14.60251202142857,
        46.850205949999996
      ],
      "data": [
        {
          "type": "Feature",
          "properties": {
            "id": "3379521692",
            "osm_type": "node",
            "lat": 46.7322395,
            "lon": 14.5334437,
            "description": "nicht katasterwürdig",
            "natural": "cliff"
          },
          "geometry": {
            "type": "Point",
            "coordinates": [
              14.5334437,
              46.7322395
            ]
          }
        },
        {
          "type": "Feature",
          "properties": {
            "id": "2338670201",
            "osm_type": "node",
            "lat": 46.9907313,
            "lon": 14.943885,
            "natural": "stone"
          },
          "geometry": {
            "type": "Point",
            "coordinates": [
              14.943885,
              46.9907313
            ]
          }
        },
        {
          "type": "Feature",
          "properties": {
            "id": "2338670351",
            "osm_type": "node",
            "lat": 47.0020219,
            "lon": 14.9022011,
            "natural": "stone"
          },
          "geometry": {
            "type": "Point",
            "coordinates": [
              14.9022011,
              47.0020219
            ]
          }
        },
        {
          "type": "Feature",
          "properties": {
            "id": "2338670355",
            "osm_type": "node",
            "lat": 47.0024843,
            "lon": 14.9013823,
            "natural": "stone"
          },
          "geometry": {
            "type": "Point",
            "coordinates": [
              14.9013823,
              47.0024843
            ]
          }
        },
        {
          "type": "Feature",
          "properties": {
            "id": "2338670360",
            "osm_type": "node",
            "lat": 47.0050911,
            "lon": 14.8973462,
            "natural": "stone"
          },
          "geometry": {
            "type": "Point",
            "coordinates": [
              14.8973462,
              47.0050911
            ]
          }
        },
        {
          "type": "Feature",
          "properties": {
            "id": "9794224893",
            "osm_type": "node",
            "lat": 47.0094054,
            "lon": 15.2377917,
            "natural": "reef"
          },
          "geometry": {
            "type": "Point",
            "coordinates": [
              15.2377917,
              47.0094054
            ]
          }
        },
        {
          "type": "Feature",
          "properties": {
            "id": "2219640135",
            "osm_type": "node",
            "lat": 46.796197,
            "lon": 14.35846,
            "description": "Pinge",
            "natural": "sinkhole"
          },
          "geometry": {
            "type": "Point",
            "coordinates": [
              14.35846,
              46.796197
            ]
          }
        },
        {
          "type": "Feature",
          "properties": {
            "id": "3379378100",
            "osm_type": "node",
            "lat": 46.740739,
            "lon": 14.424706,
            "natural": "sinkhole"
          },
          "geometry": {
            "type": "Point",
            "coordinates": [
              14.424706,
              46.740739
            ]
          }
        },
        {
          "type": "Feature",
          "properties": {
            "id": "3379378101",
            "osm_type": "node",
            "lat": 46.740416,
            "lon": 14.424932,
            "natural": "sinkhole"
          },
          "geometry": {
            "type": "Point",
            "coordinates": [
              14.424932,
              46.740416
            ]
          }
        },
        {
          "type": "Feature",
          "properties": {
            "id": "4032457509",
            "osm_type": "node",
            "lat": 46.7971803,
            "lon": 14.3591558,
            "description": "Mundlochpinge",
            "natural": "sinkhole"
          },
          "geometry": {
            "type": "Point",
            "coordinates": [
              14.3591558,
              46.7971803
            ]
          }
        },
        {
          "type": "Feature",
          "properties": {
            "id": "4032457512",
            "osm_type": "node",
            "lat": 46.7967524,
            "lon": 14.3589967,
            "description": "runde Pinge",
            "natural": "sinkhole"
          },
          "geometry": {
            "type": "Point",
            "coordinates": [
              14.3589967,
              46.7967524
            ]
          }
        },
        {
          "type": "Feature",
          "properties": {
            "id": "4032457513",
            "osm_type": "node",
            "lat": 46.7966825,
            "lon": 14.3588754,
            "description": "längliche Pinge",
            "natural": "sinkhole"
          },
          "geometry": {
            "type": "Point",
            "coordinates": [
              14.3588754,
              46.7966825
            ]
          }
        },
        {
          "type": "Feature",
          "properties": {
            "id": "4757213636",
            "osm_type": "node",
            "lat": 46.7034915,
            "lon": 14.3001403,
            "natural": "sinkhole"
          },
          "geometry": {
            "type": "Point",
            "coordinates": [
              14.3001403,
              46.7034915
            ]
          }
        },
        {
          "type": "Feature",
          "properties": {
            "id": "12073410022",
            "osm_type": "node",
            "lat": 46.7894511,
            "lon": 14.4338521,
            "natural": "stone"
          },
          "geometry": {
            "type": "Point",
            "coordinates": [
              14.4338521,
              46.7894511
            ]
          }
        }
      ],
      "children": []
    }
  ]
}